Metadata-Version: 1.0
Name: halran
Version: 0.0.7
Summary: New random algorythm
Home-page: UNKNOWN
Author: UNKNOWN
Author-email: halolxz@gmail.com
License: UNKNOWN
Platform: UNKNOWN
